{"Id":"dec20b02-ed35-4765-9454-d20388188bbc","ContentId":"home","ProjectId":"501673aa-d4c1-4437-8b71-1d1401a485ff","ContentSource":"Page","ContentType":"html","Slug":"home","IsDraftHx":false,"WasDeleted":false,"ArchivedUtc":"2019-01-03T16:10:25.1033267Z","ArchivedBy":"admin","Title":"Home","Author":"Admin","CorrelationKey":null,"Content":"<p>Under construction.</p>\r\n","CategoriesCsv":null,"PubDate":"2019-01-03T15:24:16.3965553Z","LastModified":"2019-01-03T15:24:16.4054394Z","IsPublished":true,"CreatedUtc":"2019-01-03T15:24:16.3911459Z","CreatedByUser":"admin","LastModifiedByUser":"admin","DraftContent":null,"DraftAuthor":null,"DraftPubDate":null,"SerializedModel":null,"DraftSerializedModel":null,"MetaDescription":null,"MetaJson":null,"MetaHtml":null,"TemplateKey":null,"Serializer":null,"ParentId":"0","ParentSlug":"","PageOrder":2,"ViewRoles":null,"TeaserOverride":null}